PdfInfoExtractor/Utilities.py
PdfInfoExtractor/__init__.py
PdfInfoExtractor-0.1.25.dist-info/METADATA
PdfInfoExtractor-0.1.25.dist-info/WHEEL
PdfInfoExtractor-0.1.25.dist-info/top_level.txt
PdfInfoExtractor-0.1.25.dist-info/RECORD
